odoo/addons/hr_department_code/README.rst
odoo/addons/hr_department_code/__init__.py
odoo/addons/hr_department_code/__manifest__.py
odoo/addons/hr_department_code/i18n/de.po
odoo/addons/hr_department_code/i18n/hr.po
odoo/addons/hr_department_code/i18n/hr_department_code.pot
odoo/addons/hr_department_code/i18n/it.po
odoo/addons/hr_department_code/models/__init__.py
odoo/addons/hr_department_code/models/hr_department.py
odoo/addons/hr_department_code/readme/CONTRIBUTORS.md
odoo/addons/hr_department_code/readme/DESCRIPTION.md
odoo/addons/hr_department_code/static/description/icon.png
odoo/addons/hr_department_code/static/description/index.html
odoo/addons/hr_department_code/tests/__init__.py
odoo/addons/hr_department_code/tests/test_hr_department_code.py
odoo/addons/hr_department_code/views/hr_department_views.xml
odoo_addon_hr_department_code-18.0.1.0.0.3.dist-info/METADATA
odoo_addon_hr_department_code-18.0.1.0.0.3.dist-info/WHEEL
odoo_addon_hr_department_code-18.0.1.0.0.3.dist-info/top_level.txt
odoo_addon_hr_department_code-18.0.1.0.0.3.dist-info/RECORD
